sage_otp/__init__.py
sage_otp/admin.py
sage_otp/apps.py
sage_otp/helpers/__init__.py
sage_otp/helpers/choices.py
sage_otp/helpers/exceptions.py
sage_otp/helpers/type_hints.py
sage_otp/management/__init__.py
sage_otp/management/commands/__init__.py
sage_otp/management/commands/generate_otp_data.py
sage_otp/migrations/__init__.py
sage_otp/models.py
sage_otp/repository/__init__.py
sage_otp/repository/generator/__init__.py
sage_otp/repository/generator/data_generator.py
sage_otp/repository/managers/__init__.py
sage_otp/repository/managers/otp.py
sage_otp/repository/service/__init__.py
sage_otp/repository/service/otp.py
sage_otp/tests/test_helpers.py
sage_otp/tests/test_manager.py
sage_otp/tests/test_models.py
sage_otp/tests/test_service.py
sage_otp/utils/__init__.py
sage_otp/utils/generate.py
django_sage_otp-0.1.2.dist-info/LICENSE
django_sage_otp-0.1.2.dist-info/METADATA
django_sage_otp-0.1.2.dist-info/WHEEL
django_sage_otp-0.1.2.dist-info/RECORD
