Metadata-Version: 2.1
Name: django-sage-otp
Version: 0.1.2
Summary: A Django package for managing Otp
Home-page: https://github.com/sageteamorg/django-sage-otp
License: MIT
Keywords: django,otp,django-packages
Author: Sepehr Akbarzadeh
Author-email: sepehr@sageteam.org
Requires-Python: >=3.8,<4.0
Classifier: Development Status :: 3 - Alpha
Classifier: Intended Audience :: Developers
Classifier: License :: OSI Approved :: MIT License
Classifier: Operating System :: OS Independent
Classifier: Programming Language :: Python
Classifier: Programming Language :: Python :: 3
Classifier: Programming Language :: Python :: 3.8
Classifier: Programming Language :: Python :: 3.9
Classifier: Programming Language :: Python :: 3.10
Classifier: Programming Language :: Python :: 3.11
Classifier: Programming Language :: Python :: 3.12
Classifier: Programming Language :: Python :: 3 :: Only
Requires-Dist: django (>=4.2,<5.0) ; python_version >= "3.8" and python_version < "3.10"
Requires-Dist: django (>=4.2,<5.3) ; python_version >= "3.10"
Requires-Dist: django-import-export (>=4.1.1,<5.0.0)
Requires-Dist: django-sage-tools (>=0.3.5,<0.4.0)
Requires-Dist: tqdm (>=4.66.5,<5.0.0)
Project-URL: Documentation, https://django-sage-otp.readthedocs.io
Project-URL: Issues, https://github.com/sageteamorg/django-sage-otp/issues
Project-URL: Repository, https://github.com/sageteamorg/django-sage-otp
Project-URL: Source Code, https://github.com/sageteamorg/django-sage-otp
